<?xml version="1.0" encoding="utf-8"?>
<!DOCTYPE documentInfo>
<documentInfo url="/home/rbarriga/doctorado/corn/unsorted_papers/1-s2.0-0378429089900725-main.pdf">
 <pageList/>
 <generalInfo>
  <history>
   <oldPage viewport="10;C2:0.499466:0.0773519:1"/>
   <oldPage viewport="9;C2:0.499466:0.112195:1"/>
   <oldPage viewport="8;C2:0.499466:0.0271777:1"/>
   <oldPage viewport="7;C2:0.499466:0.220209:1"/>
   <oldPage viewport="6;C2:0.499466:0.374216:1"/>
   <oldPage viewport="5;C2:0.499466:0.32892:1"/>
   <oldPage viewport="4;C2:0.499466:0.800697:1"/>
   <oldPage viewport="3;C2:0.499466:0.556794:1"/>
   <oldPage viewport="2;C2:0.499466:0.0341463:1"/>
   <oldPage viewport="1;C2:0.499466:0.406272:1"/>
   <current viewport="0;C2:0.499466:0.341463:1"/>
  </history>
  <views>
   <view name="PageView">
    <zoom mode="1" value="1.47621"/>
   </view>
  </views>
 </generalInfo>
</documentInfo>
